py_oculus_touch/__init__.py
py_oculus_touch/api.py
py_oculus_touch/oculus_touch.py
py_oculus_touch-0.1.0.dist-info/LICENSE
py_oculus_touch-0.1.0.dist-info/METADATA
py_oculus_touch-0.1.0.dist-info/WHEEL
py_oculus_touch-0.1.0.dist-info/top_level.txt
py_oculus_touch-0.1.0.dist-info/RECORD
